plugin.py
lektor_all_in_one_accessibility-1.0.0.dist-info/licenses/LICENSE
lektor_all_in_one_accessibility-1.0.0.dist-info/METADATA
lektor_all_in_one_accessibility-1.0.0.dist-info/WHEEL
lektor_all_in_one_accessibility-1.0.0.dist-info/entry_points.txt
lektor_all_in_one_accessibility-1.0.0.dist-info/top_level.txt
lektor_all_in_one_accessibility-1.0.0.dist-info/RECORD
