Metadata-Version: 2.4
Name: lektor-all-in-one-accessibility
Version: 1.0.0
Summary: Website accessibility widget for improving WCAG 2.0, 2.1, 2.2 and ADA compliance!
Author: Skynet Technologies USA LLC
Author-email: developer3@skynettechnologies.com
License: MIT
Classifier: Framework :: Lektor
Classifier: Environment :: Plugins
Classifier: License :: OSI Approved :: MIT License
Requires-Python: >=3.6
License-File: LICENSE
Requires-Dist: requests
Dynamic: author
Dynamic: author-email
Dynamic: classifier
Dynamic: description
Dynamic: description-content-type
Dynamic: license
Dynamic: license-file
Dynamic: requires-dist
Dynamic: requires-python
Dynamic: summary
